setup.py
airbrake/__init__.py
airbrake/airbrake.py
airbrake_flask.egg-info/PKG-INFO
airbrake_flask.egg-info/SOURCES.txt
airbrake_flask.egg-info/dependency_links.txt
airbrake_flask.egg-info/not-zip-safe
airbrake_flask.egg-info/requires.txt
airbrake_flask.egg-info/top_level.txt