Metadata-Version: 1.0
Name: airbrake-flask
Version: 0.0.4
Summary: airbrake-flask - Airbrake client for Python Flask
Home-page: https://github.com/kienpham2000/airbrake-flask
Author: Kien Pham, Kane Kim
Author-email: kien@sendgrid.com
License: MIT
Keywords: error airbrake flask exception
Platform: UNKNOWN
Classifier: Environment :: Console
Classifier: Intended Audience :: Developers
Classifier: License :: OSI Approved :: MIT License
Classifier: Operating System :: OS Independent
Classifier: Programming Language :: Python :: 2
Classifier: Topic :: Software Development :: Quality Assurance
Classifier: Topic :: Software Development :: Testing
Classifier: Development Status :: 5 - Production/Stable
